shock_cooling_curve/__init__.py
shock_cooling_curve/filter_info.csv
shock_cooling_curve/fitter.py
shock_cooling_curve/plotter.py
shock_cooling_curve/supernova.py
shock_cooling_curve/filters/ATLAS.c.dat
shock_cooling_curve/filters/ATLAS.o.dat
shock_cooling_curve/filters/PanSTARRS.clear.dat
shock_cooling_curve/filters/Swift_UVOT.M2.dat
shock_cooling_curve/filters/Swift_UVOT.W1.dat
shock_cooling_curve/filters/Swift_UVOT.W2.dat
shock_cooling_curve/filters/Swift_UVOT.bs.dat
shock_cooling_curve/filters/Swift_UVOT.us.dat
shock_cooling_curve/filters/Swift_UVOT.vs.dat
shock_cooling_curve/models/__init__.py
shock_cooling_curve/models/piro_2015.py
shock_cooling_curve/models/piro_2020.py
shock_cooling_curve/models/sw_bsg.py
shock_cooling_curve/models/sw_rsg.py
shock_cooling_curve/utils/__init__.py
shock_cooling_curve/utils/utils.py
shock_cooling_curve-0.0.4.dist-info/LICENSE
shock_cooling_curve-0.0.4.dist-info/METADATA
shock_cooling_curve-0.0.4.dist-info/WHEEL
shock_cooling_curve-0.0.4.dist-info/top_level.txt
shock_cooling_curve-0.0.4.dist-info/RECORD
