Metadata-Version: 2.1
Name: shock-cooling-curve
Version: 0.0.4
Summary: A python module used to model the shock cooling emission from double-peaked supernovae.
Author-email: Padma Venkatraman <vpadma@berkeley.edu>, Wynn Jacabson Galan <wynnjg@berkeley.edu>
Maintainer-email: Padma Venkatraman <vpadma@berkeley.edu>
License: MIT License
Project-URL: Repository, https://github.com/padma18-vb/shock-cooling
Keywords: core collapse supernovae,shock cooling emission,double peaked lightcurves,non-linear least squares fitting,MCMC sampling
Classifier: Programming Language :: Python :: 3
Classifier: Operating System :: MacOS :: MacOS X
Classifier: Operating System :: Microsoft :: Windows
Requires-Python: >=3.8
License-File: LICENSE
Requires-Dist: numpy
Requires-Dist: scipy
Requires-Dist: matplotlib
Requires-Dist: pysynphot
Requires-Dist: configparser
Requires-Dist: regex
Requires-Dist: corner
Requires-Dist: pandas
Requires-Dist: extinction
Requires-Dist: IPython
Requires-Dist: emcee
Requires-Dist: importlib-metadata >=1.0 ; python_version < "3.8"
